ksub/__init__.py
ksub/config.py
ksub/correction.py
ksub/decompress.py
ksub/get_subtitles.py
ksub/subhd.py
ksub/subsearch.py
ksub/unrar.exe
ksub/utils.py
ksub/zimuku.py
ksub-1.3.20.dist-info/LICENSE
ksub-1.3.20.dist-info/METADATA
ksub-1.3.20.dist-info/WHEEL
ksub-1.3.20.dist-info/entry_points.txt
ksub-1.3.20.dist-info/top_level.txt
ksub-1.3.20.dist-info/RECORD
