Metadata-Version: 2.1
Name: ksub
Version: 1.3.20
Summary: ksub: Find a best match subtitle for movie or series.
Home-page: UNKNOWN
Author: kagura
Author-email: xcehnz@foxmail.com
License: MIT
Keywords: subtitles,zimuku,subhd
Platform: UNKNOWN
Requires-Python: >=2.7
Requires-Dist: requests
Requires-Dist: bs4
Requires-Dist: unrar
Requires-Dist: six
Requires-Dist: guessit
Requires-Dist: rarfile
